avclass/__init__.py
avclass/common.py
avclass/evaluate.py
avclass/labeler.py
avclass/misp.py
avclass/normalize.py
avclass/update.py
avclass/data/andropup.expansion
avclass/data/default.expansion
avclass/data/default.tagging
avclass/data/default.taxonomy
avclass_malicialab-2.8.10.dist-info/LICENSE
avclass_malicialab-2.8.10.dist-info/METADATA
avclass_malicialab-2.8.10.dist-info/WHEEL
avclass_malicialab-2.8.10.dist-info/entry_points.txt
avclass_malicialab-2.8.10.dist-info/top_level.txt
avclass_malicialab-2.8.10.dist-info/RECORD
