Metadata-Version: 2.1
Name: avclass-malicialab
Version: 2.8.10
Summary: AVClass is a Python package and command line tool to tag / label malware samples.
Author: MaliciaLab
License: MIT License
Project-URL: Homepage, https://github.com/malicialab/avclass
Keywords: malware,malware family,tag,AV label
Classifier: License :: OSI Approved :: MIT License
Classifier: Programming Language :: Python
Classifier: Programming Language :: Python :: 3
Classifier: Topic :: Security
License-File: LICENSE
